<?xml version="1.0" encoding="utf-8" ?><dwsync><file name="filelist.xml" server="ftp.schuleduernten.ch" local="3309082223" remote="54864247332" /><file name="header.htm" server="ftp.schuleduernten.ch" local="3309082223" remote="46274312740" /><file name="image001.png" server="ftp.schuleduernten.ch" local="3309082219" remote="54864247332" /><file name="image002.png" server="ftp.schuleduernten.ch" local="3309082220" remote="54864247332" /><file name="image003.gif" server="ftp.schuleduernten.ch" local="3309082220" remote="54864247332" /><file name="image004.pct" server="ftp.schuleduernten.ch" local="3309082220" remote="54864247332" /><file name="image005.png" server="ftp.schuleduernten.ch" local="3309082220" remote="54864247332" /><file name="image006.gif" server="ftp.schuleduernten.ch" local="3309082220" remote="54864247332" /><file name="image007.pct" server="ftp.schuleduernten.ch" local="3309082220" remote="54864247332" /><file name="image008.png" server="ftp.schuleduernten.ch" local="3309082220" remote="54864247392" /><file name="image009.gif" server="ftp.schuleduernten.ch" local="3309082220" remote="54864247392" /><file name="image010.pct" server="ftp.schuleduernten.ch" local="3309082220" remote="54864247392" /><file name="image011.png" server="ftp.schuleduernten.ch" local="3309082220" remote="54864247392" /><file name="image012.gif" server="ftp.schuleduernten.ch" local="3309082220" remote="54864247392" /><file name="image013.pct" server="ftp.schuleduernten.ch" local="3309082220" remote="54864247392" /><file name="image014.png" server="ftp.schuleduernten.ch" local="3309082220" remote="54864247392" /><file name="image015.gif" server="ftp.schuleduernten.ch" local="3309082220" remote="54864247392" /><file name="image016.pct" server="ftp.schuleduernten.ch" local="3309082220" remote="54864247392" /><file name="image017.png" server="ftp.schuleduernten.ch" local="3309082221" remote="54864247392" /><file name="image018.gif" server="ftp.schuleduernten.ch" local="3309082221" remote="54864247392" /><file name="image019.pct" server="ftp.schuleduernten.ch" local="3309082221" remote="54864247392" /><file name="image020.png" server="ftp.schuleduernten.ch" local="3309082221" remote="54864247392" /><file name="image021.gif" server="ftp.schuleduernten.ch" local="3309082221" remote="54864247392" /><file name="image022.pct" server="ftp.schuleduernten.ch" local="3309082221" remote="54864247392" /><file name="image023.png" server="ftp.schuleduernten.ch" local="3309082221" remote="54864247392" /><file name="image024.gif" server="ftp.schuleduernten.ch" local="3309082221" remote="54864247392" /><file name="image025.pct" server="ftp.schuleduernten.ch" local="3309082221" remote="54864247392" /><file name="image026.png" server="ftp.schuleduernten.ch" local="3309082221" remote="54864247392" /><file name="image027.gif" server="ftp.schuleduernten.ch" local="3309082221" remote="54864247392" /><file name="image028.pct" server="ftp.schuleduernten.ch" local="3309082221" remote="54864247392" /><file name="image029.png" server="ftp.schuleduernten.ch" local="3309082221" remote="54864247392" /><file name="image030.jpg" server="ftp.schuleduernten.ch" local="3309082221" remote="54864247392" /><file name="image031.jpg" server="ftp.schuleduernten.ch" local="3309082221" remote="54864247392" /><file name="image032.pct" server="ftp.schuleduernten.ch" local="3309082221" remote="54864247392" /><file name="image033.png" server="ftp.schuleduernten.ch" local="3309082221" remote="54864247392" /><file name="image034.gif" server="ftp.schuleduernten.ch" local="3309082221" remote="54864247392" /><file name="image035.pct" server="ftp.schuleduernten.ch" local="3309082221" remote="54864247392" /><file name="image036.png" server="ftp.schuleduernten.ch" local="3309082221" remote="54864247392" /><file name="image037.pct" server="ftp.schuleduernten.ch" local="3309082221" remote="54864247392" /><file name="image038.png" server="ftp.schuleduernten.ch" local="3309082221" remote="54864247392" /><file name="image039.gif" server="ftp.schuleduernten.ch" local="3309082221" remote="54864247392" /><file name="image040.pct" server="ftp.schuleduernten.ch" local="3309082221" remote="54864247392" /><file name="image041.png" server="ftp.schuleduernten.ch" local="3309082221" remote="54864247392" /><file name="image042.gif" server="ftp.schuleduernten.ch" local="3309082222" remote="54864247392" /><file name="image043.pct" server="ftp.schuleduernten.ch" local="3309082222" remote="54864247392" /><file name="image044.png" server="ftp.schuleduernten.ch" local="3309082222" remote="54864247392" /><file name="image045.gif" server="ftp.schuleduernten.ch" local="3309082222" remote="54864247392" /><file name="image046.pct" server="ftp.schuleduernten.ch" local="3309082222" remote="54864247392" /><file name="image047.png" server="ftp.schuleduernten.ch" local="3309082222" remote="54864247392" /><file name="image048.gif" server="ftp.schuleduernten.ch" local="3309082222" remote="54864247392" /><file name="image049.pct" server="ftp.schuleduernten.ch" local="3309082222" remote="54864247392" /><file name="image050.png" server="ftp.schuleduernten.ch" local="3309082222" remote="54864247392" /><file name="image051.gif" server="ftp.schuleduernten.ch" local="3309082222" remote="54864247392" /><file name="image052.pct" server="ftp.schuleduernten.ch" local="3309082222" remote="54864247392" /><file name="image053.png" server="ftp.schuleduernten.ch" local="3309082222" remote="54864247392" /><file name="image054.gif" server="ftp.schuleduernten.ch" local="3309082222" remote="54864247392" /><file name="image055.pct" server="ftp.schuleduernten.ch" local="3309082222" remote="54864247392" /><file name="image056.png" server="ftp.schuleduernten.ch" local="3309082223" remote="54864247392" /><file name="image057.gif" server="ftp.schuleduernten.ch" local="3309082223" remote="54864247392" /><file name="image058.pct" server="ftp.schuleduernten.ch" local="3309082223" remote="54864247392" /><file name="image059.png" server="ftp.schuleduernten.ch" local="3309082223" remote="54864247392" /><file name="image060.gif" server="ftp.schuleduernten.ch" local="3309082223" remote="54864247392" /><file name="image061.pct" server="ftp.schuleduernten.ch" local="3309082223" remote="54864247392" /><file name="image062.png" server="ftp.schuleduernten.ch" local="3309082223" remote="54864247392" /><file name="image063.gif" server="ftp.schuleduernten.ch" local="3309082223" remote="54864247392" /><file name="image064.pct" server="ftp.schuleduernten.ch" local="3309082223" remote="54864247392" /><file name="image065.png" server="ftp.schuleduernten.ch" local="3309082223" remote="54864247392" /><file name="image066.gif" server="ftp.schuleduernten.ch" local="3309082223" remote="54864247392" /><file name="image067.pct" server="ftp.schuleduernten.ch" local="3309082223" remote="54864247392" /><file name="filelist.xml" server="ftp.ruediheimlicher.ch" local="3309082223" remote="11975742272" /><file name="header.htm" server="ftp.ruediheimlicher.ch" local="3309082223" remote="11975742272" /><file name="image001.png" server="ftp.ruediheimlicher.ch" local="3309082219" remote="11975742272" /><file name="image002.png" server="ftp.ruediheimlicher.ch" local="3309082220" remote="11975742272" /><file name="image003.gif" server="ftp.ruediheimlicher.ch" local="3309082220" remote="11975742272" /><file name="image004.pct" server="ftp.ruediheimlicher.ch" local="3309082220" remote="11975742272" /><file name="image005.png" server="ftp.ruediheimlicher.ch" local="3309082220" remote="11975742272" /><file name="image006.gif" server="ftp.ruediheimlicher.ch" local="3309082220" remote="11975742272" /><file name="image007.pct" server="ftp.ruediheimlicher.ch" local="3309082220" remote="11975742272" /><file name="image008.png" server="ftp.ruediheimlicher.ch" local="3309082220" remote="11975742272" /><file name="image009.gif" server="ftp.ruediheimlicher.ch" local="3309082220" remote="11975742272" /><file name="image010.pct" server="ftp.ruediheimlicher.ch" local="3309082220" remote="11975742272" /><file name="image011.png" server="ftp.ruediheimlicher.ch" local="3309082220" remote="11975742272" /><file name="image012.gif" server="ftp.ruediheimlicher.ch" local="3309082220" remote="11975742272" /><file name="image013.pct" server="ftp.ruediheimlicher.ch" local="3309082220" remote="11975742272" /><file name="image014.png" server="ftp.ruediheimlicher.ch" local="3309082220" remote="11975742272" /><file name="image015.gif" server="ftp.ruediheimlicher.ch" local="3309082220" remote="11975742272" /><file name="image016.pct" server="ftp.ruediheimlicher.ch" local="3309082220" remote="11975742272" /><file name="image017.png" server="ftp.ruediheimlicher.ch" local="3309082221" remote="11975742272" /><file name="image018.gif" server="ftp.ruediheimlicher.ch" local="3309082221" remote="11975742272" /><file name="image019.pct" server="ftp.ruediheimlicher.ch" local="3309082221" remote="11975742272" /><file name="image020.png" server="ftp.ruediheimlicher.ch" local="3309082221" remote="11975742272" /><file name="image021.gif" server="ftp.ruediheimlicher.ch" local="3309082221" remote="11975742272" /><file name="image022.pct" server="ftp.ruediheimlicher.ch" local="3309082221" remote="11975742272" /><file name="image023.png" server="ftp.ruediheimlicher.ch" local="3309082221" remote="11975742272" /><file name="image024.gif" server="ftp.ruediheimlicher.ch" local="3309082221" remote="11975742272" /><file name="image025.pct" server="ftp.ruediheimlicher.ch" local="3309082221" remote="11975742272" /><file name="image026.png" server="ftp.ruediheimlicher.ch" local="3309082221" remote="11975742272" /><file name="image027.gif" server="ftp.ruediheimlicher.ch" local="3309082221" remote="11975742272" /><file name="image028.pct" server="ftp.ruediheimlicher.ch" local="3309082221" remote="11975742272" /><file name="image029.png" server="ftp.ruediheimlicher.ch" local="3309082221" remote="11975742272" /><file name="image030.jpg" server="ftp.ruediheimlicher.ch" local="3309082221" remote="11975742272" /><file name="image031.jpg" server="ftp.ruediheimlicher.ch" local="3309082221" remote="11975742272" /><file name="image032.pct" server="ftp.ruediheimlicher.ch" local="3309082221" remote="11975742272" /><file name="image033.png" server="ftp.ruediheimlicher.ch" local="3309082221" remote="11975742272" /><file name="image034.gif" server="ftp.ruediheimlicher.ch" local="3309082221" remote="11975742272" /><file name="image035.pct" server="ftp.ruediheimlicher.ch" local="3309082221" remote="11975742272" /><file name="image036.png" server="ftp.ruediheimlicher.ch" local="3309082221" remote="11975742272" /><file name="image037.pct" server="ftp.ruediheimlicher.ch" local="3309082221" remote="11975742272" /><file name="image038.png" server="ftp.ruediheimlicher.ch" local="3309082221" remote="11975742272" /><file name="image039.gif" server="ftp.ruediheimlicher.ch" local="3309082221" remote="11975742272" /><file name="image040.pct" server="ftp.ruediheimlicher.ch" local="3309082221" remote="11975742272" /><file name="image041.png" server="ftp.ruediheimlicher.ch" local="3309082221" remote="11975742272" /><file name="image042.gif" server="ftp.ruediheimlicher.ch" local="3309082222" remote="11975742272" /><file name="image043.pct" server="ftp.ruediheimlicher.ch" local="3309082222" remote="11975742272" /><file name="image044.png" server="ftp.ruediheimlicher.ch" local="3309082222" remote="11975742332" /><file name="image045.gif" server="ftp.ruediheimlicher.ch" local="3309082222" remote="11975742332" /><file name="image046.pct" server="ftp.ruediheimlicher.ch" local="3309082222" remote="11975742332" /><file name="image047.png" server="ftp.ruediheimlicher.ch" local="3309082222" remote="11975742332" /><file name="image048.gif" server="ftp.ruediheimlicher.ch" local="3309082222" remote="11975742332" /><file name="image049.pct" server="ftp.ruediheimlicher.ch" local="3309082222" remote="11975742332" /><file name="image050.png" server="ftp.ruediheimlicher.ch" local="3309082222" remote="11975742332" /><file name="image051.gif" server="ftp.ruediheimlicher.ch" local="3309082222" remote="11975742332" /><file name="image052.pct" server="ftp.ruediheimlicher.ch" local="3309082222" remote="11975742332" /><file name="image053.png" server="ftp.ruediheimlicher.ch" local="3309082222" remote="11975742332" /><file name="image054.gif" server="ftp.ruediheimlicher.ch" local="3309082222" remote="11975742332" /><file name="image055.pct" server="ftp.ruediheimlicher.ch" local="3309082222" remote="11975742332" /><file name="image056.png" server="ftp.ruediheimlicher.ch" local="3309082223" remote="11975742332" /><file name="image057.gif" server="ftp.ruediheimlicher.ch" local="3309082223" remote="11975742332" /><file name="image058.pct" server="ftp.ruediheimlicher.ch" local="3309082223" remote="11975742332" /><file name="image059.png" server="ftp.ruediheimlicher.ch" local="3309082223" remote="11975742332" /><file name="image060.gif" server="ftp.ruediheimlicher.ch" local="3309082223" remote="11975742332" /><file name="image061.pct" server="ftp.ruediheimlicher.ch" local="3309082223" remote="11975742332" /><file name="image062.png" server="ftp.ruediheimlicher.ch" local="3309082223" remote="11975742332" /><file name="image063.gif" server="ftp.ruediheimlicher.ch" local="3309082223" remote="11975742332" /><file name="image064.pct" server="ftp.ruediheimlicher.ch" local="3309082223" remote="11975742332" /><file name="image065.png" server="ftp.ruediheimlicher.ch" local="3309082223" remote="11975742332" /><file name="image066.gif" server="ftp.ruediheimlicher.ch" local="3309082223" remote="11975742332" /><file name="image067.pct" server="ftp.ruediheimlicher.ch" local="3309082223" remote="11975742332" /></dwsync>